jupyterhub_share/__init__.py
jupyterhub_share/_version.py
jupyterhub_share/api.py
jupyterhub_share/orm.py
jupyterhub_share/pages.py
jupyterhub_share/share/templates/spawn.html
jupyterhub_share-0.1.4.dist-info/METADATA
jupyterhub_share-0.1.4.dist-info/WHEEL
jupyterhub_share-0.1.4.dist-info/licenses/LICENSE
jupyterhub_share-0.1.4.dist-info/RECORD
