Metadata-Version: 2.3
Name: jupyterhub-share
Version: 0.1.4
Summary: JupyterHub Share feature. Enables to easily share chosen UserOptions.
Author-email: Tim Kreuzer <t.kreuzer@fz-juelich.de>
License: BSD 3-Clause License
License-File: LICENSE
Keywords: jupyterhub
Requires-Python: >=3.11
Requires-Dist: escapism
Requires-Dist: jinja2
Requires-Dist: jupyterhub>=4.0.0
Requires-Dist: traitlets
Requires-Dist: urllib3
